spatialfix/__init__.py
spatialfix/spatialfix.py
spatialfix-0.1.0.dist-info/LICENSE
spatialfix-0.1.0.dist-info/METADATA
spatialfix-0.1.0.dist-info/WHEEL
spatialfix-0.1.0.dist-info/top_level.txt
spatialfix-0.1.0.dist-info/RECORD
